aliendev_cdk/__init__.py
aliendev_cdk/config/mongo.py
aliendev_cdk/config/rabbit.py
aliendev_cdk/main.py
aliendev_cdk/service/deployService.py
aliendev_cdk/service/loginService.py
aliendev_cdk/service/logoutService.py
aliendev_cdk/service/registerService.py
aliendev_cdk/service/template/README.md
aliendev_cdk/service/template/helper/test_get.py
aliendev_cdk/service/template/helper/test_post.py
aliendev_cdk/service/template/lib/stack.py
aliendev_cdk/service/templateService.py
aliendev_cdk-0.1.39.dist-info/METADATA
aliendev_cdk-0.1.39.dist-info/WHEEL
aliendev_cdk-0.1.39.dist-info/entry_points.txt
aliendev_cdk-0.1.39.dist-info/RECORD
