Metadata-Version: 2.1
Name: aliendev-cdk
Version: 0.1.39
Summary: 
Author: Nasri Adzlani
Author-email: nasri@jkt1.ebdesk.com
Requires-Python: >=3.7,<4.0
Classifier: Programming Language :: Python :: 3
Classifier: Programming Language :: Python :: 3.7
Classifier: Programming Language :: Python :: 3.8
Classifier: Programming Language :: Python :: 3.9
Classifier: Programming Language :: Python :: 3.10
Classifier: Programming Language :: Python :: 3.11
Requires-Dist: configparser (>=5.3.0,<6.0.0)
Requires-Dist: pika (>=1.3.1,<2.0.0)
Requires-Dist: pymongo (>=4.3.3,<5.0.0)
Requires-Dist: typer (>=0.7.0,<0.8.0)
